pyrtms/__init__.py
pyrtms/__main__.py
pyrtms/rtmsBrukerMCFReader.py
pyrtms/utils.py
pyrtms-0.4.0.dist-info/METADATA
pyrtms-0.4.0.dist-info/WHEEL
pyrtms-0.4.0.dist-info/entry_points.txt
pyrtms-0.4.0.dist-info/top_level.txt
pyrtms-0.4.0.dist-info/RECORD
